setup.py
function_timer.egg-info/PKG-INFO
function_timer.egg-info/SOURCES.txt
function_timer.egg-info/dependency_links.txt
function_timer.egg-info/not-zip-safe
function_timer.egg-info/top_level.txt
timer/__init__.py
timer/timer.py