Metadata-Version: 1.0
Name: function-timer
Version: 0.1
Summary: count function execution time
Home-page: https://github.com/wuling31715/algorithm/tree/master/timer
Author: 蕭擎軒
Author-email: wuling31715@gmail.com
License: MIT
Platform: UNKNOWN
